faster_outlines-2024.11.14.dist-info/METADATA
faster_outlines-2024.11.14.dist-info/LICENSE-APACHE
faster_outlines-2024.11.14.dist-info/top_level.txt
faster_outlines-2024.11.14.dist-info/WHEEL
faster_outlines-2024.11.14.dist-info/RECORD
faster_outlines-2024.11.14.dist-info/LICENSE
faster_outlines-2024.11.14.dist-info/LICENSE-MIT
faster_outlines/__init__.py
faster_outlines/lib.pypy310-pp73-aarch64-linux-gnu.so
faster_outlines/sampling.py
faster_outlines/patch.py
faster_outlines/fsm/guide.py
faster_outlines/fsm/__init__.py
faster_outlines/fsm/regex.py
faster_outlines/fsm/fsm_utils.pyi
faster_outlines/fsm/vllm_guide.py
