Metadata-Version: 2.1
Name: faster_outlines
Version: 2024.11.14
Summary: Faster, lazy backend for the `Outlines` library
Home-page: https://github.com/unaidedelf8777/faster-outlines/
Author: Nathan Hoos
Author-email: thwackyy.y@gmail.com
License: Apache 2.0
Classifier: Programming Language :: Rust
Classifier: Programming Language :: Python :: Implementation :: CPython
Requires-Python: >=3.9
License-File: LICENSE
License-File: LICENSE-APACHE
License-File: LICENSE-MIT
Requires-Dist: torch
Requires-Dist: interegular
Provides-Extra: dev
Requires-Dist: setuptools-rust>1.9.0; extra == "dev"
